.gitignore
.travis.yml
CHANGES.rst
README.rst
development.ini
setup.cfg
setup.py
kotti_newsitem/__init__.py
kotti_newsitem/fanstatic.py
kotti_newsitem/resources.py
kotti_newsitem/views.py
kotti_newsitem.egg-info/PKG-INFO
kotti_newsitem.egg-info/SOURCES.txt
kotti_newsitem.egg-info/dependency_links.txt
kotti_newsitem.egg-info/entry_points.txt
kotti_newsitem.egg-info/not-zip-safe
kotti_newsitem.egg-info/requires.txt
kotti_newsitem.egg-info/top_level.txt
kotti_newsitem/locale/README
kotti_newsitem/locale/kotti_newsitem.pot
kotti_newsitem/locale/de/LC_MESSAGES/kotti_newsitem.mo
kotti_newsitem/locale/de/LC_MESSAGES/kotti_newsitem.po
kotti_newsitem/static/css/style.css
kotti_newsitem/static/css/style.min.css
kotti_newsitem/templates/all_news.pt
kotti_newsitem/templates/news_item.pt
kotti_newsitem/templates/news_listing.pt
kotti_newsitem/templates/recent_news.pt
kotti_newsitem/tests/conftest.py
kotti_newsitem/tests/test_configure.py
kotti_newsitem/tests/test_resources.py
kotti_newsitem/tests/test_views.py